cloi/__init__.py
cloi/__main__.py
cloi-1.0.0.dist-info/DESCRIPTION.rst
cloi-1.0.0.dist-info/METADATA
cloi-1.0.0.dist-info/RECORD
cloi-1.0.0.dist-info/WHEEL
cloi-1.0.0.dist-info/metadata.json
cloi-1.0.0.dist-info/top_level.txt
