Metadata-Version: 2.0
Name: cloi
Version: 1.0.0
Summary: A wrapper to the xtralien library
Home-page: https://github.com/Xtralien/pycloi.git
Author: Xtralien
Author-email: jack@xtralien.com
License: GPLv3
Platform: UNKNOWN
Requires-Dist: xtralien
